[{"image":"/images/story17_c_t.png",
"audio":"/audios/story17_c_m.mp3",
"text":"小朋友不想借玩具、借圖書給我，我可以怎樣做"},
{"image":"/images/story17_p1_t.png",
"audio":"/audios/story17_p1_m.mp3",
"text":"有時候，我想向小朋友借玩具、借圖書，我可以嘗試先問準，後拿去"},
{"image":"/images/story17_p2_t.png",
"audio":"/audios/story17_p2_m.mp3",
"text":"有時候，小朋友想繼續玩、繼續看，所以玩具和圖書都不會借給我"},
{"image":"/images/story17_p3_t.png",
"audio":"/audios/story17_p3_m.mp3",
"text":"這時候，我可以嘗試等他們玩完、看完，才拿去"},
{"image":"/images/story17_p4_t.png",
"audio":"/audios/story17_p4_m.mp3",
"text":"又或著，等老師說交換才拿"},
{"image":"/images/story17_p5_t.png",
"audio":"/audios/story17_p5_m.mp3",
"text":"這樣做，小朋友會很開心，老師會讚我乖，讚我守次序"}]
